my_chat_package/__init__.py
my_chat_package/chat_component.py
my_chat_package/static/chat.html
my_chat_package/static/scripts.js
my_chat_package/static/styles.css
streamlit_chat_comp-0.1.0.dist-info/LICENSE
streamlit_chat_comp-0.1.0.dist-info/METADATA
streamlit_chat_comp-0.1.0.dist-info/WHEEL
streamlit_chat_comp-0.1.0.dist-info/top_level.txt
streamlit_chat_comp-0.1.0.dist-info/RECORD
